{
	"name": "segitiga_level2_t1",
	"plugin-id": "Sprite",
	"sid": 814416630314127,
	"isGlobal": false,
	"editorNewInstanceIsReplica": true,
	"instanceVariables": [
		{
			"name": "bentuk",
			"type": "string",
			"desc": "Tipe bentuk geometri item ini",
			"show": true,
			"sid": 100000000000016
		},
		{
			"name": "X_origin",
			"type": "number",
			"desc": "Posisi X awal item untuk return saat drop salah",
			"show": true,
			"sid": 939703366450008
		},
		{
			"name": "Y_origin",
			"type": "number",
			"desc": "Posisi Y awal item untuk return saat drop salah",
			"show": true,
			"sid": 600094754032696
		}
	],
	"behaviorTypes": [
		{
			"behaviorId": "DragnDrop",
			"name": "DragDrop",
			"sid": 100000000000017
		},
		{
			"behaviorId": "bound",
			"name": "BoundToLayout",
			"sid": 100000000000018
		}
	],
	"effectTypes": [],
	"animations": {
		"items": [
			{
				"frames": [
					{
						"width": 184,
						"height": 184,
						"originX": 0.5,
						"originY": 0.5,
						"originalSource": "",
						"exportFormat": "lossless",
						"exportQuality": 0.8,
						"fileType": "image/png",
						"imageSpriteId": 2658881,
						"useCollisionPoly": true,
						"duration": 1,
						"tag": ""
					}
				],
				"sid": 659607390290400,
				"name": "Default",
				"isLooping": false,
				"isPingPong": false,
				"repeatCount": 1,
				"repeatTo": 0,
				"speed": 5
			}
		],
		"subfolders": []
	}
}